tfidfpackage/PdfReader.py
tfidfpackage/__init__.py
tfidfpackage/config.py
tfidfpackage/db.py
tfidfpackage/extract.py
tfidfpackage/schema.sql
tfidfpackage/tf_idf.py
tfidfpackage/tfidf.py
tfidfpackage-1.0.4.dist-info/LICENSE
tfidfpackage-1.0.4.dist-info/METADATA
tfidfpackage-1.0.4.dist-info/WHEEL
tfidfpackage-1.0.4.dist-info/top_level.txt
tfidfpackage-1.0.4.dist-info/RECORD
