Metadata-Version: 2.1
Name: tfidfpackage
Version: 1.0.4
Summary: Term frequency inverse document frequency
Home-page: UNKNOWN
License: UNKNOWN
Platform: UNKNOWN
Classifier: Programming Language :: Python :: 3
Classifier: Operating System :: OS Independent
Requires-Python: >=3.6
